SiPMai/__init__.py
SiPMai/gen_data/__init__.py
SiPMai/gen_data/compute_img.py
SiPMai/gen_data/gen_all_data_pipeline.py
SiPMai/gen_data/prepare_dataset.py
SiPMai/gen_data/ray_generation.py
SiPMai/gen_data/smi_molecule_simulation.py
SiPMai/gen_data/smile_generation.py
SiPMai/gen_data/util_fn.py
SiPMai/smiles/__init__.py
SiPMai/smiles/pubchem_39_200_100k.json
SiPMai/unittest/__init__.py
SiPMai/unittest/test_gen_data.py
SiPMai/unittest/test_pair_transform.py
SiPMai/utils/__init__.py
SiPMai/utils/dataloader.py
SiPMai/utils/img_transform.py
SiPMai-0.0.20.dist-info/LICENSE.md
SiPMai-0.0.20.dist-info/METADATA
SiPMai-0.0.20.dist-info/WHEEL
SiPMai-0.0.20.dist-info/entry_points.txt
SiPMai-0.0.20.dist-info/top_level.txt
SiPMai-0.0.20.dist-info/RECORD
