Metadata-Version: 2.1
Name: SiPMai
Version: 0.0.20
Summary: A Simple Yet Effective Scanning Tunnel Microscope Image Simulator
Home-page: http://github.com/GilesLuo/SiPMai
Author: Zhiyao Luo, Yaotian Yang, Jiali Li
Author-email: zhiyao.luo@eng.ox.ac.uk
License: MIT
Project-URL: Source Code, https://github.com/GilesLuo/SiPMai
Keywords: Chemistry Simulation,STM Image Synthesis
Requires-Python: >=3.6, <3.10
License-File: LICENSE.md
Requires-Dist: numpy (<1.24,>=1.16)
Requires-Dist: torch (>=1.4.0)
Requires-Dist: packaging
Requires-Dist: tqdm
Requires-Dist: scikit-learn
Requires-Dist: matplotlib
Requires-Dist: scipy
Requires-Dist: pandas
Requires-Dist: opencv-python
Requires-Dist: numba
Requires-Dist: rdkit
Requires-Dist: ray
Provides-Extra: dev
Requires-Dist: flake8 ; extra == 'dev'
Requires-Dist: pytest ; extra == 'dev'
Requires-Dist: pytest-cov ; extra == 'dev'
Requires-Dist: mypy ; extra == 'dev'
